field_properties/__init__.py
field_properties/field_properties.py
field_properties/py.typed
field_properties/unwrap_properties.py
field_properties-0.1.dist-info/LICENSE
field_properties-0.1.dist-info/METADATA
field_properties-0.1.dist-info/WHEEL
field_properties-0.1.dist-info/top_level.txt
field_properties-0.1.dist-info/RECORD
