Metadata-Version: 2.1
Name: field-properties
Version: 0.1
Summary: Properties for dataclass fields
Home-page: https://github.com/wyfo/field-properties
Author: Joseph Perez
Author-email: joperez@hotmail.fr
License: MIT
Platform: UNKNOWN
Classifier: Development Status :: 4 - Beta
Classifier: Intended Audience :: Developers
Classifier: License :: OSI Approved :: MIT License
Classifier: Programming Language :: Python :: 3.6
Classifier: Programming Language :: Python :: 3.7
Classifier: Programming Language :: Python :: 3.8
Classifier: Programming Language :: Python :: 3.9
Classifier: Topic :: Software Development :: Libraries :: Python Modules
Requires-Python: >=3.6
Requires-Dist: dataclasses (==0.7) ; python_version < "3.7"
